{"textures":{"0":"modelengine:entity/smaug","particle":"#0"},"elements":[{"from":[2.0170002,5.683464,-2.026184],"to":[14.293,10.612465,17.162811],"faces":{"east":{"uv":[3.0625,11.40625,3.21094,11.44531],"tintindex":0,"rotation":0,"texture":"#0"},"north":{"uv":[11.4375,7.25,11.53125,7.28906],"tintindex":0,"rotation":0,"texture":"#0"},"west":{"uv":[11.40625,3.34375,11.55469,3.38281],"tintindex":0,"rotation":0,"texture":"#0"},"up":{"uv":[2.59375,10.92969,2.5,10.78125],"tintindex":0,"rotation":0,"texture":"#0"},"down":{"uv":[7.375,11.1875,7.28125,11.33594],"tintindex":0,"rotation":0,"texture":"#0"}}}],"display":{"head":{"rotation":[0.0,0.0,0.0]},"firstperson_righthand":{"rotation":[0.0,0.0,0.0]},"thirdperson_lefthand":{"rotation":[0.0,-0.0,-0.0]},"firstperson_lefthand":{"rotation":[0.0,-0.0,-0.0]},"fixed":{"rotation":[0.0,0.0,0.0]},"ground":{"rotation":[0.0,0.0,0.0]},"thirdperson_righthand":{"rotation":[0.0,0.0,0.0]},"gui":{"rotation":[-150.0,-45.0,180.0]}}}