{
    "model": {
        "type": "range_dispatch",
        "property": "custom_model_data",
        "fallback": {
            "type": "model",
            "model": "minecraft:item/iron_leggings"
        },
        "entries": [
            {
                "threshold": 1,
                "model": {
                    "type": "minecraft:model",
                    "model": "minecraft:item/rohan/rohan_leggings"
                }
            },
			{
                "threshold": 2,
                "model": {
                    "type": "minecraft:model",
                    "model": "minecraft:item/gondor/gondor_leggings"
                }
            },
			{
                "threshold": 3,
                "model": {
                    "type": "minecraft:model",
                    "model": "minecraft:item/mithril/mithril_leggings"
                }
            },
			{
                "threshold": 4,
                "model": {
                    "type": "minecraft:model",
                    "model": "minecraft:item/elven/elf_leggings"
                }
            },
			{
                "threshold": 5,
                "model": {
                    "type": "minecraft:model",
                    "model": "minecraft:item/dwarf/armor1/dwarf_leggings"
                }
            },
			{
                "threshold": 6,
                "model": {
                    "type": "minecraft:model",
                    "model": "minecraft:item/dwarf/armor2/dwarf_leggings"
                }
            },
			{
                "threshold": 7,
                "model": {
                    "type": "minecraft:model",
                    "model": "minecraft:item/dwarf/armor3/dwarf_leggings"
                }
            },
			{
                "threshold": 8,
                "model": {
                    "type": "minecraft:model",
                    "model": "minecraft:item/dwarf/armor4/dwarf_leggings"
                }
            },
			{
                "threshold": 9,
                "model": {
                    "type": "minecraft:model",
                    "model": "minecraft:item/dwarf/armor5/dwarf_leggings"
                }
            },
			{
                "threshold": 10,
                "model": {
                    "type": "minecraft:model",
                    "model": "minecraft:item/armor/evil/evil_leggings"
                }
            },
			{
                "threshold": 11,
                "model": {
                    "type": "minecraft:model",
                    "model": "minecraft:item/armor/gold_robe/gold_robe_leggings"
                }
            },
			{
                "threshold": 12,
                "model": {
                    "type": "minecraft:model",
                    "model": "minecraft:item/armor/plate/plate_leggings"
                }
            },
			{
                "threshold": 13,
                "model": {
                    "type": "minecraft:model",
                    "model": "minecraft:item/armor/yellowtabard/yellowtabard_leggings"
                }
            },
			{
                "threshold": 14,
                "model": {
                    "type": "minecraft:model",
                    "model": "minecraft:item/armor/evil/evil2_leggings"
                }
            },
			{
                "threshold": 15,
                "model": {
                    "type": "minecraft:model",
                    "model": "minecraft:item/armor/ghost/ghost_leggings"
                }
            },
			{
                "threshold": 16,
                "model": {
                    "type": "minecraft:model",
                    "model": "minecraft:item/armor/raven/raven_leggings"
                }
            },
			{
                "threshold": 17,
                "model": {
                    "type": "minecraft:model",
                    "model": "minecraft:item/armor/allorn/allorn_leggings"
                }
            },
			{
                "threshold": 18,
                "model": {
                    "type": "minecraft:model",
                    "model": "minecraft:item/armor/purple_robe/purple_robe_leggings"
                }
            },
			{
                "threshold": 19,
                "model": {
                    "type": "minecraft:model",
                    "model": "minecraft:item/armor/patchwork/patchwork_leggings"
                }
            },
			{
                "threshold": 20,
                "model": {
                    "type": "minecraft:model",
                    "model": "minecraft:item/armor/leathercoat/leathercoat_leggings"
                }
            },
			{
                "threshold": 21,
                "model": {
                    "type": "minecraft:model",
                    "model": "minecraft:item/armor/lilacrobe/lilacrobe_leggings"
                }
            },
			{
                "threshold": 22,
                "model": {
                    "type": "minecraft:model",
                    "model": "minecraft:item/armor/crusade/crusade_leggings"
                }
            },
			{
                "threshold": 23,
                "model": {
                    "type": "minecraft:model",
                    "model": "minecraft:item/armor/oathbroken/oathbroken_leggings"
                }
            },
			{
                "threshold": 24,
                "model": {
                    "type": "minecraft:model",
                    "model": "minecraft:item/armor/wasp/wasp_leggings"
                }
            },
			{
                "threshold": 25,
                "model": {
                    "type": "minecraft:model",
                    "model": "minecraft:item/armor/cyanrobe/cyanrobe_leggings"
                }
            },
			{
                "threshold": 26,
                "model": {
                    "type": "minecraft:model",
                    "model": "minecraft:item/armor/bluerobe/bluerobe_leggings"
                }
            },
			{
                "threshold": 27,
                "model": {
                    "type": "minecraft:model",
                    "model": "minecraft:item/armor/crimsonknight/crimsonknight_leggings"
                }
            },
			{
                "threshold": 28,
                "model": {
                    "type": "minecraft:model",
                    "model": "minecraft:item/armor/jaderobe/jaderobe_leggings"
                }
            },
			{
                "threshold": 29,
                "model": {
                    "type": "minecraft:model",
                    "model": "minecraft:item/armor/warlord/warlord_leggings"
                }
            },
			{
                "threshold": 30,
                "model": {
                    "type": "minecraft:model",
                    "model": "minecraft:item/armor/warden/warden_leggings"
                }
            },
			{
                "threshold": 31,
                "model": {
                    "type": "minecraft:model",
                    "model": "minecraft:item/armor/necromancer/necromancer_leggings"
                }
            },
			{
                "threshold": 32,
                "model": {
                    "type": "minecraft:model",
                    "model": "minecraft:item/armor/thunderbolt/thunderbolt_leggings"
                }
            },
			{
                "threshold": 33,
                "model": {
                    "type": "minecraft:model",
                    "model": "minecraft:item/armor/goldplate/goldplate_leggings"
                }
            },
			{
                "threshold": 34,
                "model": {
                    "type": "minecraft:model",
                    "model": "minecraft:item/armor/welshplate/welshplate_leggings"
                }
            },
			{
                "threshold": 35,
                "model": {
                    "type": "minecraft:model",
                    "model": "minecraft:item/armor/orangerobe/orangerobe_leggings"
                }
            },
			{
                "threshold": 36,
                "model": {
                    "type": "minecraft:model",
                    "model": "minecraft:item/armor/greenrobe/greenrobe_leggings"
                }
            },
			{
                "threshold": 37,
                "model": {
                    "type": "minecraft:model",
                    "model": "minecraft:item/armor/bloodcaster/bloodcaster_leggings"
                }
            },
			{
                "threshold": 38,
                "model": {
                    "type": "minecraft:model",
                    "model": "minecraft:item/armor/snow/snow_leggings"
                }
            },
			{
                "threshold": 39,
                "model": {
                    "type": "minecraft:model",
                    "model": "minecraft:item/armor/purplehabit/purplehabit_leggings"
                }
            },
			{
                "threshold": 40,
                "model": {
                    "type": "minecraft:model",
                    "model": "minecraft:item/armor/tyrionplate/tyrionplate_leggings"
                }
            },
			{
                "threshold": 41,
                "model": {
                    "type": "minecraft:model",
                    "model": "minecraft:item/armor/redplate/redplate_leggings"
                }
            },
			{
                "threshold": 42,
                "model": {
                    "type": "minecraft:model",
                    "model": "minecraft:item/armor/darkplate/darkplate_leggings"
                }
            },
			{
                "threshold": 43,
                "model": {
                    "type": "minecraft:model",
                    "model": "minecraft:item/armor/darklord/darklord_leggings"
                }
            },
			{
                "threshold": 44,
                "model": {
                    "type": "minecraft:model",
                    "model": "minecraft:item/armor/lion/lion_leggings"
                }
            },
			{
                "threshold": 45,
                "model": {
                    "type": "minecraft:model",
                    "model": "minecraft:item/armor/druidrobe/druidrobe_leggings"
                }
            },
			{
                "threshold": 46,
                "model": {
                    "type": "minecraft:model",
                    "model": "minecraft:item/armor/mercenary/mercenary_leggings"
                }
            },
			{
                "threshold": 47,
                "model": {
                    "type": "minecraft:model",
                    "model": "minecraft:item/armor/harad/harad_leggings"
                }
            },
			{
                "threshold": 48,
                "model": {
                    "type": "minecraft:model",
                    "model": "minecraft:item/armor/greenplate/greenplate_leggings"
                }
            },
			{
                "threshold": 49,
                "model": {
                    "type": "minecraft:model",
                    "model": "minecraft:item/armor/bloodknight/bloodknight_leggings"
                }
            },
			{
                "threshold": 50,
                "model": {
                    "type": "minecraft:model",
                    "model": "minecraft:item/armor/redeemed/redeemed_leggings"
                }
            },
			{
                "threshold": 51,
                "model": {
                    "type": "minecraft:model",
                    "model": "minecraft:item/armor/smaug/smaug_leggings"
                }
            }
        ]
    }
}
